[
  {
    "reel_id": "reel-001",
    "file_path": "/videos/0.mp4",
    "title": "0.mp4",
    "creator": "@reel_antics",
    "category": "Comedy",
    "runtime": 102
  },
  {
    "reel_id": "reel-002",
    "file_path": "/videos/1.mp4",
    "title": "1.mp4",
    "creator": "@sippy_sambar",
    "category": "Comedy",
    "runtime": 128
  },
  {
    "reel_id": "reel-003",
    "file_path": "/videos/2.mp4",
    "title": "2.mp4",
    "creator": "@rapid_roto",
    "category": "Satire",
    "runtime": 97
  },
  {
    "reel_id": "reel-004",
    "file_path": "/videos/3.mp4",
    "title": "3.mp4",
    "creator": "@amma_ki_nazar",
    "category": "Slice of Life",
    "runtime": 115
  },
  {
    "reel_id": "reel-005",
    "file_path": "/videos/4.mp4",
    "title": "4.mp4",
    "creator": "@cubicle_chacha",
    "category": "Comedy",
    "runtime": 141
  },
  {
    "reel_id": "reel-006",
    "file_path": "/videos/5.mp4",
    "title": "5.mp4",
    "creator": "@forward_this",
    "category": "Satire",
    "runtime": 88
  },
  {
    "reel_id": "reel-007",
    "file_path": "/videos/6.mp4",
    "title": "6.mp4",
    "creator": "@cc_all",
    "category": "Comedy",
    "runtime": 112
  }
]
